<?xml version="1.0" encoding="UTF-8"?>
<YFS_EXCEPTION_TYPEList TableName="YFS_EXCEPTION_TYPE" TotalNumberOfRecords="18">
<ExceptionType ConfigForm="" ConsolidationRequired="N"
    ConsolidationWindow="" Createprogid="XMLMigrator"
    Createts="2024-08-01T13:21:43-04:00" Createuserid="SYSTEM"
    ExceptionType="ORDER_HUB_ORDER_DELAY"
    ExceptionTypeDescription="Order Delay"
    ExceptionTypeKey="2024080113214313301" ExpirationDays="0"
    FollowUpHours="0.00" HighPriorityThreshold="0.00" IsConfigurable="N"
    ListForm="" Lockid="0" Modifyprogid="XMLMigrator"
    Modifyts="2024-08-01T13:21:43-04:00" Modifyuserid="SYSTEM"
    OrganizationCode="DEFAULT" Priority="1.00" QueueId=""
    QueueOwnerKey="DEFAULT" ResolutionForm=""/>
<ExceptionType ConfigForm="" ConsolidationRequired="N"
    ConsolidationWindow="" Createprogid="XMLMigrator"
    Createts="2024-08-01T13:21:43-04:00" Createuserid="SYSTEM"
    ExceptionType="ORDER_HUB_SHIPMENT_DELAY"
    ExceptionTypeDescription="Shipment Delay"
    ExceptionTypeKey="2024080113214313302" ExpirationDays="0"
    FollowUpHours="0.00" HighPriorityThreshold="0.00" IsConfigurable="N"
    ListForm="" Lockid="0" Modifyprogid="XMLMigrator"
    Modifyts="2024-08-01T13:21:43-04:00" Modifyuserid="SYSTEM"
    OrganizationCode="DEFAULT" Priority="1.00" QueueId=""
    QueueOwnerKey="DEFAULT" ResolutionForm=""/>
<ExceptionType ConfigForm="" ConsolidationRequired="N"
    ConsolidationWindow="" Createprogid="XMLMigrator"
    Createts="2024-08-01T13:23:59-04:00" Createuserid="SYSTEM"
    ExceptionType="YCD_VERIFY_ADDRESS"
    ExceptionTypeDescription="Verify Address"
    ExceptionTypeKey="2024080113235920876" ExpirationDays="0"
    FollowUpHours="0.00" HighPriorityThreshold="0.00" IsConfigurable="N"
    ListForm="" Lockid="0" Modifyprogid="XMLMigrator"
    Modifyts="2024-08-01T13:23:59-04:00" Modifyuserid="SYSTEM"
    OrganizationCode="DEFAULT" Priority="1.00"
    QueueId="YCD_VERIFY_ADDRESS" QueueOwnerKey="DEFAULT" ResolutionForm="com.yantra.pca.ycd.rcp.tasks.alert.screens.YCDAlertDetails_VERIFY_ADDRESS"/>
<ExceptionType ConfigForm="" ConsolidationRequired="N"
    ConsolidationWindow="" Createprogid="XMLMigrator"
    Createts="2024-08-01T13:23:59-04:00" Createuserid="SYSTEM"
    ExceptionType="YCD_PAYMENT_FAILURE"
    ExceptionTypeDescription="Payment Failure"
    ExceptionTypeKey="2024080113235920877" ExpirationDays="0"
    FollowUpHours="0.00" HighPriorityThreshold="0.00" IsConfigurable="N"
    ListForm="" Lockid="0" Modifyprogid="XMLMigrator"
    Modifyts="2024-08-01T13:23:59-04:00" Modifyuserid="SYSTEM"
    OrganizationCode="DEFAULT" Priority="1.00"
    QueueId="YCD_PAYMENT_DECLINED" QueueOwnerKey="DEFAULT" ResolutionForm="com.yantra.pca.ycd.rcp.tasks.alert.screens.YCDAlertDetails_PAYMENT_FAILURE"/>
<ExceptionType ConfigForm="" ConsolidationRequired="N"
    ConsolidationWindow="" Createprogid="XMLMigrator"
    Createts="2024-08-01T13:23:59-04:00" Createuserid="SYSTEM"
    ExceptionType="YCD_DUPLICATE_ORDER"
    ExceptionTypeDescription="Duplicate Order"
    ExceptionTypeKey="2024080113235920878" ExpirationDays="0"
    FollowUpHours="0.00" HighPriorityThreshold="0.00" IsConfigurable="N"
    ListForm="" Lockid="0" Modifyprogid="XMLMigrator"
    Modifyts="2024-08-01T13:23:59-04:00" Modifyuserid="SYSTEM"
    OrganizationCode="DEFAULT" Priority="1.00"
    QueueId="YCD_DUPLICATE_ORDER" QueueOwnerKey="DEFAULT" ResolutionForm="com.yantra.pca.ycd.rcp.tasks.alert.screens.YCDAlertDetails_DUPLICATE_ORDER"/>
<ExceptionType ConfigForm="" ConsolidationRequired="N"
    ConsolidationWindow="" Createprogid="XMLMigrator"
    Createts="2024-08-01T13:23:59-04:00" Createuserid="SYSTEM"
    ExceptionType="YCD_ORDER_CANCEL_NOTICE"
    ExceptionTypeDescription="Order Cancel"
    ExceptionTypeKey="2024080113235920879" ExpirationDays="0"
    FollowUpHours="0.00" HighPriorityThreshold="0.00" IsConfigurable="N"
    ListForm="" Lockid="0" Modifyprogid="XMLMigrator"
    Modifyts="2024-08-01T13:23:59-04:00" Modifyuserid="SYSTEM"
    OrganizationCode="DEFAULT" Priority="1.00"
    QueueId="YCD_CUSTOMER_NOTIFICATION" QueueOwnerKey="DEFAULT" ResolutionForm="com.yantra.pca.ycd.rcp.tasks.alert.screens.YCDAlertDetails_ORDER_CANCEL_NOTICE"/>
<ExceptionType ConfigForm="" ConsolidationRequired="N"
    ConsolidationWindow="" Createprogid="XMLMigrator"
    Createts="2024-08-01T13:23:59-04:00" Createuserid="SYSTEM"
    ExceptionType="YCD_PRICE_MATCH"
    ExceptionTypeDescription="Price Match"
    ExceptionTypeKey="2024080113235920880" ExpirationDays="0"
    FollowUpHours="0.00" HighPriorityThreshold="0.00" IsConfigurable="N"
    ListForm="" Lockid="0" Modifyprogid="XMLMigrator"
    Modifyts="2024-08-01T13:23:59-04:00" Modifyuserid="SYSTEM"
    OrganizationCode="DEFAULT" Priority="1.00" QueueId="YCD_PRICE_MATCH"
    QueueOwnerKey="DEFAULT" ResolutionForm="com.yantra.pca.ycd.rcp.tasks.alert.screens.YCDPriceMatchAlert"/>
<ExceptionType ConfigForm="" ConsolidationRequired="N"
    ConsolidationWindow="" Createprogid="XMLMigrator"
    Createts="2024-08-01T13:23:59-04:00" Createuserid="SYSTEM"
    ExceptionType="YCD_RESHIP" ExceptionTypeDescription="Reship"
    ExceptionTypeKey="2024080113235920881" ExpirationDays="0"
    FollowUpHours="0.00" HighPriorityThreshold="0.00" IsConfigurable="N"
    ListForm="" Lockid="0" Modifyprogid="XMLMigrator"
    Modifyts="2024-08-01T13:23:59-04:00" Modifyuserid="SYSTEM"
    OrganizationCode="DEFAULT" Priority="1.00" QueueId="YCD_RESHIP"
    QueueOwnerKey="DEFAULT" ResolutionForm="com.yantra.pca.ycd.rcp.tasks.alert.screens.YCDAlertDetailsComposite"/>
<ExceptionType ConfigForm="" ConsolidationRequired="N"
    ConsolidationWindow="" Createprogid="XMLMigrator"
    Createts="2024-08-01T13:23:59-04:00" Createuserid="SYSTEM"
    ExceptionType="YCD_BACKORDER_NOTICE"
    ExceptionTypeDescription="Back Order Notice"
    ExceptionTypeKey="2024080113235920882" ExpirationDays="0"
    FollowUpHours="0.00" HighPriorityThreshold="0.00" IsConfigurable="N"
    ListForm="" Lockid="0" Modifyprogid="XMLMigrator"
    Modifyts="2024-08-01T13:23:59-04:00" Modifyuserid="SYSTEM"
    OrganizationCode="DEFAULT" Priority="1.00"
    QueueId="YCD_CUSTOMER_NOTIFICATION" QueueOwnerKey="DEFAULT" ResolutionForm="com.yantra.pca.ycd.rcp.tasks.alert.screens.YCDAlertDetails_BACKORDER_NOTICE"/>
<ExceptionType ConfigForm="" ConsolidationRequired="N"
    ConsolidationWindow="" Createprogid="XMLMigrator"
    Createts="2024-08-01T13:23:59-04:00" Createuserid="SYSTEM"
    ExceptionType="YCD_FRAUD_CHECK"
    ExceptionTypeDescription="Fraud Check Notice"
    ExceptionTypeKey="2024080113235920883" ExpirationDays="0"
    FollowUpHours="0.00" HighPriorityThreshold="0.00" IsConfigurable="N"
    ListForm="" Lockid="0" Modifyprogid="XMLMigrator"
    Modifyts="2024-08-01T13:23:59-04:00" Modifyuserid="SYSTEM"
    OrganizationCode="DEFAULT" Priority="1.00"
    QueueId="YCD_CUSTOMER_NOTIFICATION" QueueOwnerKey="DEFAULT" ResolutionForm="com.yantra.pca.ycd.rcp.tasks.alert.screens.YCDAlertDetails_FRAUD_CHECK"/>
<ExceptionType ConfigForm="" ConsolidationRequired="N"
    ConsolidationWindow="" Createprogid="XMLMigrator"
    Createts="2024-08-01T13:23:59-04:00" Createuserid="SYSTEM"
    ExceptionType="YCD_FTC_NOTIFICATION"
    ExceptionTypeDescription="FTC Notification"
    ExceptionTypeKey="2024080113235920884" ExpirationDays="0"
    FollowUpHours="0.00" HighPriorityThreshold="0.00" IsConfigurable="N"
    ListForm="" Lockid="0" Modifyprogid="XMLMigrator"
    Modifyts="2024-08-01T13:23:59-04:00" Modifyuserid="SYSTEM"
    OrganizationCode="DEFAULT" Priority="1.00"
    QueueId="YCD_CUSTOMER_NOTIFICATION" QueueOwnerKey="DEFAULT" ResolutionForm="com.yantra.pca.ycd.rcp.tasks.alert.screens.YCDAlertDetails_FTC_NOTICE"/>
<ExceptionType ConfigForm="" ConsolidationRequired="N"
    ConsolidationWindow="" Createprogid="XMLMigrator"
    Createts="2024-08-01T13:23:59-04:00" Createuserid="SYSTEM"
    ExceptionType="UIEXCEPTION" ExceptionTypeDescription="UI Exception"
    ExceptionTypeKey="2024080113235920885" ExpirationDays="0"
    FollowUpHours="0.00" HighPriorityThreshold="0.00" IsConfigurable="N"
    ListForm="" Lockid="0" Modifyprogid="XMLMigrator"
    Modifyts="2024-08-01T13:23:59-04:00" Modifyuserid="SYSTEM"
    OrganizationCode="DEFAULT" Priority="1.00" QueueId="DEFAULT"
    QueueOwnerKey="DEFAULT" ResolutionForm="com.yantra.pca.ycd.rcp.tasks.alert.screens.YCDAlertDetailsComposite"/>
<ExceptionType ConfigForm="" ConsolidationRequired="N"
    ConsolidationWindow="" Createprogid="XMLMigrator"
    Createts="2024-08-01T13:23:59-04:00" Createuserid="SYSTEM"
    ExceptionType="AGENTEXCEPTION"
    ExceptionTypeDescription="Agent Exception"
    ExceptionTypeKey="2024080113235920886" ExpirationDays="0"
    FollowUpHours="0.00" HighPriorityThreshold="0.00" IsConfigurable="N"
    ListForm="" Lockid="0" Modifyprogid="XMLMigrator"
    Modifyts="2024-08-01T13:23:59-04:00" Modifyuserid="SYSTEM"
    OrganizationCode="DEFAULT" Priority="1.00" QueueId="DEFAULT"
    QueueOwnerKey="DEFAULT" ResolutionForm="com.yantra.pca.ycd.rcp.tasks.alert.screens.YCDAlertDetailsComposite"/>
<ExceptionType ConfigForm="" ConsolidationRequired="N"
    ConsolidationWindow="" Createprogid="XMLMigrator"
    Createts="2024-08-01T13:23:59-04:00" Createuserid="SYSTEM"
    ExceptionType="YCD_STOP_DELIVERY"
    ExceptionTypeDescription="Stop Delivery"
    ExceptionTypeKey="2024080113235920887" ExpirationDays="0"
    FollowUpHours="0.00" HighPriorityThreshold="0.00" IsConfigurable="N"
    ListForm="" Lockid="0" Modifyprogid="XMLMigrator"
    Modifyts="2024-08-01T13:23:59-04:00" Modifyuserid="SYSTEM"
    OrganizationCode="DEFAULT" Priority="1.00"
    QueueId="YCD_STOP_DELIVERY" QueueOwnerKey="DEFAULT" ResolutionForm="com.yantra.pca.ycd.rcp.tasks.alert.screens.YCDAlertDetailsComposite"/>
<ExceptionType ConfigForm="" ConsolidationRequired="N"
    ConsolidationWindow="" Createprogid="XMLMigrator"
    Createts="2024-08-01T13:23:59-04:00" Createuserid="SYSTEM"
    ExceptionType="YCD_ANNOUNCEMENT"
    ExceptionTypeDescription="Announcement"
    ExceptionTypeKey="2024080113235920888" ExpirationDays="0"
    FollowUpHours="0.00" HighPriorityThreshold="0.00" IsConfigurable="N"
    ListForm="" Lockid="0" Modifyprogid="XMLMigrator"
    Modifyts="2024-08-01T13:23:59-04:00" Modifyuserid="SYSTEM"
    OrganizationCode="DEFAULT" Priority="1.00" QueueId=""
    QueueOwnerKey="DEFAULT" ResolutionForm="com.yantra.pca.ycd.rcp.tasks.announcement.screens.YCDAnnouncementDetailsPage"/>
<ExceptionType ConfigForm="" ConsolidationRequired="N"
    ConsolidationWindow="" Createprogid="XMLMigrator"
    Createts="2024-08-01T13:23:59-04:00" Createuserid="SYSTEM"
    ExceptionType="YCD_ORDER_APPROVAL"
    ExceptionTypeDescription="Order Approval"
    ExceptionTypeKey="2024080113235920889" ExpirationDays="0"
    FollowUpHours="0.00" HighPriorityThreshold="0.00" IsConfigurable="N"
    ListForm="" Lockid="0" Modifyprogid="XMLMigrator"
    Modifyts="2024-08-01T13:23:59-04:00" Modifyuserid="SYSTEM"
    OrganizationCode="DEFAULT" Priority="1.00" QueueId=""
    QueueOwnerKey="DEFAULT" ResolutionForm="com.yantra.pca.ycd.rcp.tasks.alert.screens.YCDAlertDetailsComposite"/>
<ExceptionType ConfigForm="" ConsolidationRequired="N"
    ConsolidationWindow="" Createprogid="XMLMigrator"
    Createts="2024-08-01T13:23:59-04:00" Createuserid="SYSTEM"
    ExceptionType="YCD_HOT_PICK" ExceptionTypeDescription="Hot Pick"
    ExceptionTypeKey="2024080113235920890" ExpirationDays="0"
    FollowUpHours="0.00" HighPriorityThreshold="0.00" IsConfigurable="N"
    ListForm="" Lockid="0" Modifyprogid="XMLMigrator"
    Modifyts="2024-08-01T13:23:59-04:00" Modifyuserid="SYSTEM"
    OrganizationCode="DEFAULT" Priority="1.00" QueueId="DEFAULT"
    QueueOwnerKey="DEFAULT" ResolutionForm=""/>
<ExceptionType ConfigForm="" ConsolidationRequired="N"
    ConsolidationWindow="" Createprogid="XMLMigrator"
    Createts="2024-08-01T13:23:59-04:00" Createuserid="SYSTEM"
    ExceptionType="YCD_NEAR_SLA" ExceptionTypeDescription="Nearing SLA"
    ExceptionTypeKey="2024080113235920891" ExpirationDays="0"
    FollowUpHours="0.00" HighPriorityThreshold="0.00" IsConfigurable="N"
    ListForm="" Lockid="0" Modifyprogid="XMLMigrator"
    Modifyts="2024-08-01T13:23:59-04:00" Modifyuserid="SYSTEM"
    OrganizationCode="DEFAULT" Priority="1.00" QueueId="DEFAULT"
    QueueOwnerKey="DEFAULT" ResolutionForm=""/>
</YFS_EXCEPTION_TYPEList>